RTL/barrel_shifter.v
`timescale 1ns / 1ps
/////////////////////////////////////////////////////////////////////////////////////////////////////////////////////////////////////////////
// Author: Ioannins Rizos
// Design Name: Tunable Approximate Booth Multiplier
// Module Name: barrel_shifter
//
// Aditional comments: This RTL code is part of the paper submission: I. Rizos, G. Papatheodorou, A. Efthymiou "Tunable Approximate Booth 
// Multiplier". Submitted for ISVLSI 2025. Code provided under the LISCENCE attached to this repository.
/////////////////////////////////////////////////////////////////////////////////////////////////////////////////////////////////////////////

module barrel_shifter #(
        parameter integer NA=8,
        parameter integer NB=8
    )(
        input  wire [NB-1:0]      B_in,
        input  wire [NA-1:0]      S_in,
        output wire [NA+NB-2:0]   N_out
    );
    
    wire [NA+NB-2:0] B_ext = {{(NA-1){B_in[NB-1]}}, B_in};          // Sign extend B_in to the full width before shifting
    
    wire [NA+NB-2:0] shift_results[0:NA-1];                         // Wire array for all possible shifts
    reg  [NA+NB-2:0] shifted_value;                                 // Shifted value register

    genvar i;
    generate
        for (i = 0; i < NA; i = i + 1) begin : Shift_Logic          // Does all possible shifts and places them in wire array
            assign shift_results[i] = B_ext << i;
        end
    endgenerate
   
    integer j;
    always @(*) begin                                               // CLK ssynchronus update
        shifted_value = {NA+NB-1{1'b0}};                            // Reset shifted_value
        for (j = 0; j < NA; j = j + 1) begin
            if (S_in[j]) begin                                      // Select the correct shifted value
                shifted_value = shifted_value | shift_results[j];
            end
        end
    end

    assign N_out = shifted_value;

endmodule

RTL/lookahead_priority_enforcer.v
`timescale 1ns / 1ps
/////////////////////////////////////////////////////////////////////////////////////////////////////////////////////////////////////////////
// Author: Aristides Efthymiou
// Design Name: Tunable Approximate Booth Multiplier
// Module Name: lookahead_penf_last
//
// Aditional comments: This RTL code is part of the paper submission: I. Rizos, G. Papatheodorou, A. Efthymiou "Tunable Approximate Booth 
// Multiplier". Submitted for ISVLSI 2025. Code provided under the LISCENCE attached to this repository.
/////////////////////////////////////////////////////////////////////////////////////////////////////////////////////////////////////////////

module ripple_penf_last #(
        parameter integer WIDTH = 4
    )( 
        input  wire                 stop_in,
        input  wire [WIDTH-1:0]     A_in,
        input  wire                 trailing1_in,
        output wire [WIDTH-1:0]     B_out,
        output wire                 stop_out,
        output wire                 last_out,
        output wire                 slicestop_out
    );

    wire [WIDTH-1:0] stop;
    wire [WIDTH-1:0] trailing;
    wire [WIDTH-1:0] last;

    genvar i;

    generate
        assign stop[WIDTH-1] = stop_in;
        for (i = WIDTH-1; i > 0; i = i - 1) begin
        assign B_out[i] = A_in[i] & ~stop[i];
        assign stop[i-1] = stop[i] | A_in[i];
        end
        assign B_out[0] = A_in[0] & ~stop[0];
        assign slicestop_out = stop[0] | A_in[0];
        assign stop_out = |A_in;

        assign trailing[0] = trailing1_in;
        assign last[0] = B_out[0] & ~trailing[0];
        for (i = 1; i < WIDTH; i = i + 1) begin
            assign trailing[i] = A_in[i-1] | trailing[i-1];
            assign last[i] = B_out[i] & ~trailing[i];
        end
        assign last_out = |last;
    endgenerate
endmodule

module lookahead_penf_last #(
        parameter integer WIDTH = 29
    )(
        input  wire [WIDTH-1:0] A_in,
        output wire [WIDTH-1:0] OH_out,
        output wire last
    );
   
    localparam integer NUM_4BIT_MODULES = WIDTH / 4;
    localparam integer REMAINING_BITS = WIDTH % 4;

    wire [NUM_4BIT_MODULES:0] stop;
    wire [NUM_4BIT_MODULES:0] lastSlice;
    
    wire finalStop;
    
    genvar i;

    generate
        if (REMAINING_BITS > 0) begin
        ripple_penf_last #(.WIDTH(REMAINING_BITS))
        u0 (.stop_in(1'b0),
            .A_in(A_in[WIDTH-1 -: REMAINING_BITS]),
            .B_out(OH_out[WIDTH-1 -: REMAINING_BITS]),
            .stop_out(stop[NUM_4BIT_MODULES]),
            .slicestop_out(),
            .trailing1_in(|stop[NUM_4BIT_MODULES-1:0]),
            .last_out(lastSlice[NUM_4BIT_MODULES])
            );
        end else begin
        assign stop[NUM_4BIT_MODULES] = 1'b0;
        assign lastSlice[NUM_4BIT_MODULES] = 1'b0;
        end

        for (i = NUM_4BIT_MODULES-1; i >= 0; i = i - 1) begin : gen4bslice
        if (i > 0) begin
            ripple_penf_last #(.WIDTH(4))
            u4b (.stop_in(|stop[NUM_4BIT_MODULES:i+1]),
                .A_in(A_in[i*4 +: 4]),
                .B_out(OH_out[i*4 +: 4]),
                .stop_out(stop[i]),
                .slicestop_out(),  // unconnected - not needed.
                .trailing1_in(|stop[i-1:0]),
                .last_out(lastSlice[i])
                );
        end else begin
            ripple_penf_last #(.WIDTH(4))
            u4b (.stop_in(|stop[NUM_4BIT_MODULES:i+1]),
                .A_in(A_in[i*4 +: 4]),
                .B_out(OH_out[i*4 +: 4]),
                .stop_out(stop[i]),
                .slicestop_out(finalStop),
                .trailing1_in(1'b0),
                .last_out(lastSlice[i])
                );
        end
        end
        assign last = |lastSlice | ~finalStop;
    endgenerate
endmodule

RTL/transition_detect.v
`timescale 1ns / 1ps
/////////////////////////////////////////////////////////////////////////////////////////////////////////////////////////////////////////////
// Author: Ioannins Rizos
// Design Name: Tunable Approximate Booth Multiplier
// Module Name: transition_detect
//
// Aditional comments: This RTL code is part of the paper submission: I. Rizos, G. Papatheodorou, A. Efthymiou "Tunable Approximate Booth 
// Multiplier". Submitted for ISVLSI 2025. Code provided under the LISCENCE attached to this repository.
/////////////////////////////////////////////////////////////////////////////////////////////////////////////////////////////////////////////


module transition_detect #(
        parameter NA = 6
    )(
        input   wire [NA-1:0]     A_in,                             // Input number
        output  wire [NA-1:0]     P_out,                            // ith bit=1 if A_in[i] -> A_in[i-1] = 0 -> 1 (positive transition)
        output  wire [NA-1:0]     N_out                             // ith bit=1 if A_in[i] -> A_in[i-1] = 1 -> 0 (negative transition)
    );

    assign P_out[0] = 0;                                            // Always 0 because of imaginary 0 after number
    assign N_out[0] = A_in[0];                                      // Equal to LSB of input because of imaginary 0 after number
    
    genvar i;
    generate
        for (i = 1; i < NA; i = i + 1) begin : MSB
            assign P_out[i] = ~A_in[i] &  A_in[i-1];                // detect positive transition
            assign N_out[i] =  A_in[i] & ~A_in[i-1];                // detect negative transition
        end
    endgenerate
endmodule

RTL/axc_booth.v
`timescale 1ns / 1ps
/////////////////////////////////////////////////////////////////////////////////////////////////////////////////////////////////////////////
// Author: Ioannins Rizos
// Design Name: Tunable Approximate Booth Multiplier
// Module Name: axc_booth
//
// Aditional comments: This RTL code is part of the paper submission: I. Rizos, G. Papatheodorou, A. Efthymiou "Tunable Approximate Booth 
// Multiplier". Submitted for ISVLSI 2025. Code provided under the LISCENCE attached to this repository.
/////////////////////////////////////////////////////////////////////////////////////////////////////////////////////////////////////////////

module axc_booth #(
        parameter integer NA=12,                                    // Bit width of A (in [2:32])
        parameter integer NB=12,                                    // Bit width of B (in [2:32] & must be NB>=NA)
        parameter integer NC=$clog2(NA)+1                           // Bit width of C ( = ceil(log2(NA))+1 )
    )(
        input   wire                 CLK,                           // Clock
        input   wire                 START,                         // Start (active-high)
        input   wire  [NA-1:0]       A_in,                          // Multiplicant
        input   wire  [NB-1:0]       B_in,                          // Multiplier
        input   wire  [NC-1:0]       C_in,                          // Ammount of Cycles to run
        output  wire  [NA+NB-1:0]    N_out,                         // Product
        output  wire                 Done_out                       // Multiplication done or ammount of cycles met 
    );

// Input Registers //////////////////////////////////////////////////////////////////////////////////////////////////////////////////////////
reg  [NB-1:0]       B_reg;                                          // B (Multiplier) register
reg  [NC-1:0]       C_reg;                                          // C (Ammount of Cycles) register

// Transition Detect Signals ////////////////////////////////////////////////////////////////////////////////////////////////////////////////
wire [NA-1:0]       Pos_trans_wire;                                 // Positive transitions wire
wire [NA-1:0]       Neg_trans_wire;                                 // Negative transitions wire
reg  [NA-1:0]       Pos_trans_reg;                                  // Positive transitions register
reg  [NA-1:0]       Neg_trans_reg;                                  // Negative transitions register

// Priority Enforcer Signals ////////////////////////////////////////////////////////////////////////////////////////////////////////////////
wire [NA-1:0]       PE_in_wire;                                     // PE input selector wire
wire [NA-1:0]       OH_wire;                                        // One-Hot wire                 
reg                 Polarity_reg;                                   // Polarity register: currently doing 0:addition or 1:subtraction 
reg  [NA-1:0]       PE_mask_reg;                                    // Mask register for priority enforcer

// Barrel Shifter Signals ///////////////////////////////////////////////////////////////////////////////////////////////////////////////////
wire [NA+NB-2:0]    PP_wire;                                        // Partial Product wire

// Acummulator Signals //////////////////////////////////////////////////////////////////////////////////////////////////////////////////////
reg  [NA+NB-1:0]    Res_reg;                                        // Result register

// State Machine Signals ////////////////////////////////////////////////////////////////////////////////////////////////////////////////////
localparam integer SC = 3;                                          // state count
localparam STATE_IDLE   = 3'b001;
localparam STATE_START  = 3'b010;
localparam STATE_MULT   = 3'b100;
reg  [SC-1:0]       State_reg;                                      // state register (one-hot)


// Transition Detect ////////////////////////////////////////////////////////////////////////////////////////////////////////////////////////
transition_detect #( .NA(NA) ) TD_inst (.A_in(A_in), .P_out(Pos_trans_wire), .N_out(Neg_trans_wire));


// Priority Enforcer ////////////////////////////////////////////////////////////////////////////////////////////////////////////////////////
wire                PE_last;                                        // PE reports that this is the last 1 in the input
reg [1:0]           Prev_PE_done;                                   // Saved previous PE was last, thus done now
reg                 Done_reg;                                       // Done_out register
assign PE_in_wire = Polarity_reg ? Neg_trans_reg & PE_mask_reg : Pos_trans_reg & PE_mask_reg;

lookahead_penf_last #( .WIDTH(NA) ) PE_inst (.A_in(PE_in_wire), .OH_out(OH_wire), .last(PE_last));


// Done_out control /////////////////////////////////////////////////////////////////////////////////////////////////////////////////////////
assign Done_out = Done_reg;
always @( posedge CLK ) begin
    case(State_reg) 
        STATE_IDLE: begin                                           // when IDLE reset
            Prev_PE_done <= 0; 
            if(START) Done_reg <= 0;
        end
        STATE_MULT: begin                                           // when MULT 
            if(Prev_PE_done[0]==0 & PE_last==1) begin               // if first PE done appears
                Prev_PE_done[0] <= 1;                               // register it
                Prev_PE_done[1] <= Polarity_reg;                    // and the polarity it appeared in
            end                                                     // then assert whether or not we are done
            Done_reg <= Done_reg | ((C_reg==0) | (Prev_PE_done[0] & PE_last & (Polarity_reg!=Prev_PE_done[1])));
        end
        default: Prev_PE_done <= 0;  
    endcase
end


// Barrel Shifter ///////////////////////////////////////////////////////////////////////////////////////////////////////////////////////////
barrel_shifter #( .NA(NA), .NB(NB) ) BS_inst (.B_in(B_reg), .S_in(OH_wire), .N_out(PP_wire));


// Acummulator //////////////////////////////////////////////////////////////////////////////////////////////////////////////////////////////
always @( posedge CLK ) begin
    if(START) begin                                                 // when START reset
        Res_reg <= 0;
    end
    else if(State_reg==STATE_MULT) begin                            // when MULT
        if(!Polarity_reg) begin                                     // Add or subtract based on Polarity_reg
            Res_reg <= Res_reg + PP_wire;
        end
        else begin
            Res_reg <= Res_reg - PP_wire;
        end
    end
end
assign N_out = Res_reg;


// State Machine ////////////////////////////////////////////////////////////////////////////////////////////////////////////////////////////
always @( posedge CLK ) begin
    case(State_reg) 
        STATE_IDLE: begin                                       
            if(START) begin                                         // IDLE -> START (when START)
                State_reg <= STATE_START;                           // set next state

                B_reg <= B_in;                                      // copy inputs B and C to registers
                C_reg <= C_in;

                PE_mask_reg <= {NA{1'b1}};                          // enable PE mask

                Polarity_reg <= 0;
            end
        end
        STATE_START: begin                                          // START -> MULT (always)
            State_reg <= STATE_MULT;                                // set next state                           
            Pos_trans_reg <= Pos_trans_wire;                        // transfer pos and neg transitions of A to registers
            Neg_trans_reg <= Neg_trans_wire;                    
        end
        STATE_MULT: begin                                       
            if(Done_out) begin                                      // MULT -> IDLE (when Done)
                State_reg <= STATE_IDLE;                            // set next state
                Pos_trans_reg <= 0;
                Neg_trans_reg <= 0;
                C_reg <= 0;                                         // kinda hacky way to keep Done_out asserted until Start again
            end
            else begin
                PE_mask_reg <= ~OH_wire & PE_mask_reg;
                Polarity_reg <= !Polarity_reg;                      // update Polarity_reg
                C_reg <= C_reg - 1;                                 // increment cycles
            end
        end
        default: State_reg <= STATE_IDLE;                           // set next state
    endcase
end

endmodule

RTL/test_bench/axc_booth_tb.v
`timescale 1ns / 1ps
/////////////////////////////////////////////////////////////////////////////////////////////////////////////////////////////////////////////
// Author: Ioannins Rizos
// Design Name: Tunable Approximate Booth Multiplier Test Bench
// Module Name: axc_booth_bt
//
// Aditional comments: This RTL code is part of the paper submission: I. Rizos, G. Papatheodorou, A. Efthymiou "Tunable Approximate Booth 
// Multiplier". Submitted for ISVLSI 2025. Code provided under the LISCENCE attached to this repository.
/////////////////////////////////////////////////////////////////////////////////////////////////////////////////////////////////////////////

module axc_booth_tb();
    parameter integer NA=8;             // Bit width of A
    parameter integer NB=8;             // Bit width of B

    reg                     CLK=1;      // Clock
    reg                     START;      // Start (active-high)
    reg   [NA-1:0]          A_in;       // Multiplicant
    reg   [NB-1:0]          B_in;       // Multiplier
    reg   [$clog2(NA):0]    C_in;       // Ammount of Cycles to run
    wire  [NA+NB-1:0]       N_out;      // Product
    wire                    Done_out;   // Multiplication done or ammount of cycles met 
    
    axc_booth #(.NA(NA), .NB(NB)) DUT (.CLK(CLK), .START(START), .A_in(A_in), .B_in(B_in), .C_in(C_in), .N_out(N_out), .Done_out(Done_out));
    
    always @(*) #1 CLK <= !CLK;         // clock oscillation

    integer i;
    initial begin
        $dumpfile("test.vcd");          // for iverilog waveform output
        $dumpvars(0,axc_booth_tb);
        
        #4;                             // initial wait

        for(i=NA; i>=1; i=i-1) begin    // for cycles in range [NA,1]
            C_in <= i;                  // the multiplications bellow will run for i cycles each

            A_in <= -1;                 // -1 x 7
            B_in <= 7;
            START <= 1;
            #2;
            START <= 0;
            #26;

            A_in <= 44;                 // 44 x 2
            B_in <= 2;
            START <= 1;
            #2;
            START <= 0;
            #26;

            A_in <= -27;                // -27 x 80
            B_in <= 80;
            START <= 1;
            #2;
            START <= 0;
            #26;

            A_in <= -127;               // -127 x 0
            B_in <= 0;
            START <= 1;
            #2;
            START <= 0;
            #26;

            A_in <= 127;                // 127 x 127
            B_in <= 127;
            START <= 1;
            #2;
            START <= 0;
            #26;

            A_in <= 85;                 // 85 x 4
            B_in <= 4;
            START <= 1;
            #2;
            START <= 0;
            #26;

            A_in <= -86;                // -86 x 4
            B_in <= 4;
            START <= 1;
            #2;
            START <= 0;
            #26;
        end

        $finish;
    end
    
endmodule

RTL/test_bench/test.vcd
$date
	Mon Mar 17 15:09:32 2025
$end
$version
	Icarus Verilog
$end
$timescale
	1ps
$end
$scope module axc_booth_tb $end
$var wire 16 ! N_out [15:0] $end
$var wire 1 " Done_out $end
$var parameter 32 # NA $end
$var parameter 32 $ NB $end
$var reg 8 % A_in [7:0] $end
$var reg 8 & B_in [7:0] $end
$var reg 1 ' CLK $end
$var reg 4 ( C_in [3:0] $end
$var reg 1 ) START $end
$var integer 32 * i [31:0] $end
$scope module DUT $end
$var wire 8 + A_in [7:0] $end
$var wire 8 , B_in [7:0] $end
$var wire 1 ' CLK $end
$var wire 4 - C_in [3:0] $end
$var wire 1 " Done_out $end
$var wire 16 . N_out [15:0] $end
$var wire 1 ) START $end
$var wire 8 / Pos_trans_wire [7:0] $end
$var wire 15 0 PP_wire [14:0] $end
$var wire 1 1 PE_last $end
$var wire 8 2 PE_in_wire [7:0] $end
$var wire 8 3 OH_wire [7:0] $end
$var wire 8 4 Neg_trans_wire [7:0] $end
$var parameter 32 5 NA $end
$var parameter 32 6 NB $end
$var parameter 32 7 NC $end
$var parameter 32 8 SC $end
$var parameter 3 9 STATE_IDLE $end
$var parameter 3 : STATE_MULT $end
$var parameter 3 ; STATE_START $end
$var reg 8 < B_reg [7:0] $end
$var reg 4 = C_reg [3:0] $end
$var reg 1 > Done_reg $end
$var reg 8 ? Neg_trans_reg [7:0] $end
$var reg 8 @ PE_mask_reg [7:0] $end
$var reg 1 A Polarity_reg $end
$var reg 8 B Pos_trans_reg [7:0] $end
$var reg 2 C Prev_PE_done [1:0] $end
$var reg 16 D Res_reg [15:0] $end
$var reg 3 E State_reg [2:0] $end
$scope module BS_inst $end
$var wire 8 F B_in [7:0] $end
$var wire 15 G N_out [14:0] $end
$var wire 8 H S_in [7:0] $end
$var wire 15 I B_ext [14:0] $end
$var parameter 32 J NA $end
$var parameter 32 K NB $end
$var reg 15 L shifted_value [14:0] $end
$var integer 32 M j [31:0] $end
$scope begin Shift_Logic[0] $end
$var parameter 2 N i $end
$upscope $end
$scope begin Shift_Logic[1] $end
$var parameter 2 O i $end
$upscope $end
$scope begin Shift_Logic[2] $end
$var parameter 3 P i $end
$upscope $end
$scope begin Shift_Logic[3] $end
$var parameter 3 Q i $end
$upscope $end
$scope begin Shift_Logic[4] $end
$var parameter 4 R i $end
$upscope $end
$scope begin Shift_Logic[5] $end
$var parameter 4 S i $end
$upscope $end
$scope begin Shift_Logic[6] $end
$var parameter 4 T i $end
$upscope $end
$scope begin Shift_Logic[7] $end
$var parameter 4 U i $end
$upscope $end
$upscope $end
$scope module PE_inst $end
$var wire 8 V A_in [7:0] $end
$var wire 1 1 last $end
$var wire 3 W stop [2:0] $end
$var wire 3 X lastSlice [2:0] $end
$var wire 1 Y finalStop $end
$var wire 8 Z OH_out [7:0] $end
$var parameter 32 [ NUM_4BIT_MODULES $end
$var parameter 32 \ REMAINING_BITS $end
$var parameter 32 ] WIDTH $end
$scope begin gen4bslice[0] $end
$var parameter 2 ^ i $end
$scope begin genblk1 $end
$scope module u4b $end
$var wire 4 _ A_in [3:0] $end
$var wire 1 Y slicestop_out $end
$var wire 1 ` stop_in $end
$var wire 1 a trailing1_in $end
$var wire 4 b trailing [3:0] $end
$var wire 1 c stop_out $end
$var wire 4 d stop [3:0] $end
$var wire 1 e last_out $end
$var wire 4 f last [3:0] $end
$var wire 4 g B_out [3:0] $end
$var parameter 32 h WIDTH $end
$scope begin genblk1[1] $end
$var parameter 2 i i $end
$upscope $end
$scope begin genblk1[2] $end
$var parameter 3 j i $end
$upscope $end
$scope begin genblk1[3] $end
$var parameter 3 k i $end
$upscope $end
$scope begin genblk2[1] $end
$var parameter 2 l i $end
$upscope $end
$scope begin genblk2[2] $end
$var parameter 3 m i $end
$upscope $end
$scope begin genblk2[3] $end
$var parameter 3 n i $end
$upscope $end
$upscope $end
$upscope $end
$upscope $end
$scope begin gen4bslice[1] $end
$var parameter 2 o i $end
$scope begin genblk1 $end
$scope module u4b $end
$var wire 4 p A_in [3:0] $end
$var wire 1 q slicestop_out $end
$var wire 1 r stop_in $end
$var wire 1 s trailing1_in $end
$var wire 4 t trailing [3:0] $end
$var wire 1 u stop_out $end
$var wire 4 v stop [3:0] $end
$var wire 1 w last_out $end
$var wire 4 x last [3:0] $end
$var wire 4 y B_out [3:0] $end
$var parameter 32 z WIDTH $end
$scope begin genblk1[1] $end
$var parameter 2 { i $end
$upscope $end
$scope begin genblk1[2] $end
$var parameter 3 | i $end
$upscope $end
$scope begin genblk1[3] $end
$var parameter 3 } i $end
$upscope $end
$scope begin genblk2[1] $end
$var parameter 2 ~ i $end
$upscope $end
$scope begin genblk2[2] $end
$var parameter 3 !" i $end
$upscope $end
$scope begin genblk2[3] $end
$var parameter 3 "" i $end
$upscope $end
$upscope $end
$upscope $end
$upscope $end
$scope begin genblk1 $end
$upscope $end
$upscope $end
$scope module TD_inst $end
$var wire 8 #" A_in [7:0] $end
$var wire 8 $" P_out [7:0] $end
$var wire 8 %" N_out [7:0] $end
$var parameter 32 &" NA $end
$scope begin MSB[1] $end
$var parameter 2 '" i $end
$upscope $end
$scope begin MSB[2] $end
$var parameter 3 (" i $end
$upscope $end
$scope begin MSB[3] $end
$var parameter 3 )" i $end
$upscope $end
$scope begin MSB[4] $end
$var parameter 4 *" i $end
$upscope $end
$scope begin MSB[5] $end
$var parameter 4 +" i $end
$upscope $end
$scope begin MSB[6] $end
$var parameter 4 ," i $end
$upscope $end
$scope begin MSB[7] $end
$var parameter 4 -" i $end
$upscope $end
$upscope $end
$upscope $end
$upscope $end
$enddefinitions $end
$comment Show the parameter values. $end
$dumpall
b111 -"
b110 ,"
b101 +"
b100 *"
b11 )"
b10 ("
b1 '"
b1000 &"
b11 ""
b10 !"
b1 ~
b11 }
b10 |
b1 {
b100 z
b1 o
b11 n
b10 m
b1 l
b11 k
b10 j
b1 i
b100 h
b0 ^
b1000 ]
b0 \
b10 [
b111 U
b110 T
b101 S
b100 R
b11 Q
b10 P
b1 O
b0 N
b1000 K
b1000 J
b10 ;
b100 :
b1 9
b11 8
b100 7
b1000 6
b1000 5
b1000 $
b1000 #
$end
#0
$dumpvars
bx %"
bx0 $"
bx #"
bx y
bx x
xw
b0xxx v
xu
bx t
xs
0r
xq
bx p
bx g
bx f
xe
bx d
xc
bx0 b
0a
x`
bx _
bx Z
xY
b0xx X
b0xx W
bx V
b1000 M
b0 L
bx I
bx H
b0 G
bx F
b1 E
bx D
b0 C
bx B
xA
bx @
bx ?
x>
bx =
bx <
bx 4
bx 3
bx 2
x1
b0 0
bx0 /
bx .
bx -
bx ,
bx +
bx *
x)
bx (
1'
bx &
bx %
x"
bx !
$end
#1000
0'
#2000
1'
#3000
0'
#4000
b1000 M
0"
0>
b0 !
b0 .
b0 D
0A
b11111111 @
b1000 =
b111 I
b111 <
b111 F
b10 E
b0 /
b0 $"
b1 4
b1 %"
1'
1)
b111 &
b111 ,
b11111111 %
b11111111 +
b11111111 #"
b1000 (
b1000 -
b1000 *
#5000
0'
#6000
11
0Y
0q
0w
b0 X
0e
b0 f
b0 x
b1000 M
b0 v
b0 y
b0 b
b0 3
b0 H
b0 Z
b0 g
b0 d
0`
b0 t
0s
0u
b0 p
b0 W
0c
b0 _
b0 2
b0 V
b1 ?
b0 B
b100 E
1'
0)
#7000
0'
#8000
b1 X
1e
b1 f
11
b111 0
b111 G
b111 L
b1000 M
b1110 b
b1 3
b1 H
b1 Z
b1 g
1Y
b1111 t
1s
b1 W
1c
b1 _
b1 2
b1 V
b1 C
b111 =
1A
1'
#9000
0'
#10000
b0 X
0e
b0 f
b1000 M
b0 0
b0 G
b0 L
b0 b
b0 3
b0 H
b0 Z
b0 g
0Y
b0 t
0s
b0 W
0c
b0 _
b0 2
b0 V
b110 =
0A
b11111110 @
b1111111111111001 !
b1111111111111001 .
b1111111111111001 D
1"
1>
1'
#11000
0'
#12000
b0 =
b0 ?
b1 E
1'
#13000
0'
#14000
b0 C
1'
#15000
0'
#16000
1'
#17000
0'
#18000
1'
#19000
0'
#20000
1'
#21000
0'
#22000
1'
#23000
0'
#24000
1'
#25000
0'
#26000
1'
#27000
0'
#28000
1'
#29000
0'
#30000
1'
#31000
0'
#32000
b1000 M
0"
0>
b0 !
b0 .
b0 D
b11111111 @
b1000 =
b10 I
b10 <
b10 F
b10 E
b1010000 /
b1010000 $"
b100100 4
b100100 %"
1'
1)
b10 &
b10 ,
b101100 %
b101100 +
b101100 #"
#33000
0'
#34000
01
1Y
b0 X
0w
b0 x
b10000000 0
b10000000 G
b10000000 L
b1000 M
b11 v
b1110 t
b1000000 3
b1000000 H
b1000000 Z
b100 y
1q
b1111 d
1`
b10 W
1u
b101 p
b1010000 2
b1010000 V
b100100 ?
b1010000 B
b100 E
1'
0)
#35000
0'
#36000
b1000 M
b1000000 0
b1000000 G
b1000000 L
b100000 3
b100000 H
b100000 Z
b10 y
b1 v
b1000 b
b1111 t
1s
b10 p
b11 W
1c
b100 _
b100100 2
b100100 V
b10000000 !
b10000000 .
b10000000 D
b111 =
1A
b10111111 @
1'
#37000
0'
#38000
11
b10 X
1w
b1 x
b1000 M
b100000 0
b100000 G
b100000 L
b10000 3
b10000 H
b10000 Z
b1 y
b0 v
b0 b
b1110 t
0s
b1 p
b10 W
0c
b0 _
b10000 2
b10000 V
b110 =
0A
b10011111 @
b1000000 !
b1000000 .
b1000000 D
1'
#39000
0'
#40000
1e
b100 f
b100 g
11
b1 X
0w
b0 x
b1000 M
b1000 0
b1000 G
b1000 L
b100 3
b100 H
b100 Z
b0 y
0q
b1000 b
b11 d
0`
b1111 t
1s
0u
b0 p
b1 W
1c
b100 _
b100 2
b100 V
b1 C
b1100000 !
b1100000 .
b1100000 D
b101 =
1A
b10001111 @
1'
#41000
0'
#42000
0Y
11
b0 X
0e
b0 f
b1000 M
b0 0
b0 G
b0 L
b0 3
b0 H
b0 Z
b0 g
b0 d
b0 b
b0 t
0s
b0 W
0c
b0 _
b0 2
b0 V
b100 =
0A
b10001011 @
b1011000 !
b1011000 .
b1011000 D
1"
1>
1'
#43000
0'
#44000
b0 =
b0 ?
b0 B
b1 E
1'
#45000
0'
#46000
b0 C
1'
#47000
0'
#48000
1'
#49000
0'
#50000
1'
#51000
0'
#52000
1'
#53000
0'
#54000
1'
#55000
0'
#56000
1'
#57000
0'
#58000
1'
#59000
0'
#60000
b1000 M
0"
0>
b0 !
b0 .
b0 D
b11111111 @
b1000 =
b1010000 I
b1010000 <
b1010000 F
b10 E
b1010 /
b1010 $"
b100101 4
b100101 %"
1'
1)
b1010000 &
b1010000 ,
b11100101 %
b11100101 +
b11100101 #"
#61000
0'
#62000
01
b0 X
0e
b0 f
1Y
b1010000000 0
b1010000000 G
b1010000000 L
b1000 M
b1000 3
b1000 H
b1000 Z
b1000 g
b111 d
b1100 b
b1111 t
1s
b1 W
1c
b1010 _
b1010 2
b1010 V
b100101 ?
b1010 B
b100 E
1'
0)
#63000
0'
#64000
1q
b1000 M
b101000000000 0
b101000000000 G
b101000000000 L
b10 y
b1 v
b100000 3
b100000 H
b100000 Z
b0 g
b1110 b
b1111 d
1`
b11 W
1u
b10 p
b101 _
b100101 2
b100101 V
b1010000000 !
b1010000000 .
b1010000000 D
b111 =
1A
b11110111 @
1'
#65000
0'
#66000
11
b1 X
1e
b10 f
b10 g
0q
b1000 M
b10100000 0
b10100000 G
b10100000 L
b10 3
b10 H
b10 Z
b0 y
b0 v
b1100 b
b1 d
0`
b1 W
0u
b0 p
b10 _
b10 2
b10 V
b110 =
0A
b11010111 @
b1111100010000000 !
b1111100010000000 .
b1111100010000000 D
1'
#67000
0'
#68000
01
b0 X
0e
b0 f
b1000 M
b101000000 0
b101000000 G
b101000000 L
b100 3
b100 H
b100 Z
b100 g
b11 d
b1110 b
b101 _
b101 2
b101 V
b1 C
b1111100100100000 !
b1111100100100000 .
b1111100100100000 D
b101 =
1A
b11010101 @
1'
#69000
0'
#70000
11
0Y
b1000 M
b0 0
b0 G
b0 L
b0 3
b0 H
b0 Z
b0 g
b0 d
b0 b
b0 t
0s
b0 W
0c
b0 _
b0 2
b0 V
b100 =
0A
b11010001 @
b1111011111100000 !
b1111011111100000 .
b1111011111100000 D
1'
#71000
0'
#72000
b1 X
1e
b1 f
11
b1010000 0
b1010000 G
b1010000 L
b1000 M
b1110 b
b1 3
b1 H
b1 Z
b1 g
1Y
b1111 t
1s
b1 W
1c
b1 _
b1 2
b1 V
b11 =
1A
1'
#73000
0'
#74000
b0 X
0e
b0 f
b1000 M
b0 0
b0 G
b0 L
b0 b
b0 3
b0 H
b0 Z
b0 g
0Y
b0 t
0s
b0 W
0c
b0 _
b0 2
b0 V
b10 =
0A
b11010000 @
b1111011110010000 !
b1111011110010000 .
b1111011110010000 D
1"
1>
1'
#75000
0'
#76000
b0 =
b0 ?
b0 B
b1 E
1'
#77000
0'
#78000
b0 C
1'
#79000
0'
#80000
1'
#81000
0'
#82000
1'
#83000
0'
#84000
1'
#85000
0'
#86000
1'
#87000
0'
#88000
b1000 M
0"
0>
b0 !
b0 .
b0 D
b11111111 @
b1000 =
b0 I
b0 <
b0 F
b10 E
b10 /
b10 $"
b10000001 4
b10000001 %"
1'
1)
b0 &
b0 ,
b10000001 %
b10000001 +
b10000001 #"
#89000
0'
#90000
b1 X
1e
b10 f
1Y
b1000 M
b10 3
b10 H
b10 Z
b10 g
b1 d
b1100 b
b1111 t
1s
b1 W
1c
b10 _
b10 2
b10 V
b10000001 ?
b10 B
b100 E
1'
0)
#91000
0'
#92000
1q
01
b0 X
0e
b0 f
b1000 M
b1000 y
b111 v
b10000000 3
b10000000 H
b10000000 Z
b0 g
b1110 b
b1111 d
1`
b11 W
1u
b1000 p
b1 _
b10000001 2
b10000001 V
b1 C
b111 =
1A
b11111101 @
1'
#93000
0'
#94000
11
0Y
0q
b1000 M
b0 3
b0 H
b0 Z
b0 y
b0 v
b0 b
b0 d
0`
b0 t
0s
0u
b0 p
b0 W
0c
b0 _
b0 2
b0 V
b110 =
0A
b1111101 @
1'
#95000
0'
#96000
b1 X
1e
b1 f
11
b1000 M
b1110 b
b1 3
b1 H
b1 Z
b1 g
1Y
b1111 t
1s
b1 W
1c
b1 _
b1 2
b1 V
b101 =
1A
1'
#97000
0'
#98000
b0 X
0e
b0 f
b1000 M
b0 b
b0 3
b0 H
b0 Z
b0 g
0Y
b0 t
0s
b0 W
0c
b0 _
b0 2
b0 V
b100 =
0A
b1111100 @
1"
1>
1'
#99000
0'
#100000
b0 =
b0 ?
b0 B
b1 E
1'
#101000
0'
#102000
b0 C
1'
#103000
0'
#104000
1'
#105000
0'
#106000
1'
#107000
0'
#108000
1'
#109000
0'
#110000
1'
#111000
0'
#112000
1'
#113000
0'
#114000
1'
#115000
0'
#116000
b1000 M
0"
0>
b11111111 @
b1000 =
b1111111 I
b1111111 <
b1111111 F
b10 E
b10000000 /
b10000000 $"
b1 4
b1 %"
1'
1)
b1111111 &
b1111111 ,
b1111111 %
b1111111 +
b1111111 #"
#117000
0'
#118000
1Y
1q
b10 X
1w
b1000 x
b11111110000000 0
b11111110000000 G
b11111110000000 L
b1000 M
b10000000 3
b10000000 H
b10000000 Z
b1000 y
b111 v
b1111 d
1`
b10 W
1u
b1000 p
b10000000 2
b10000000 V
b1 ?
b10000000 B
b100 E
1'
0)
#119000
0'
